algofunc/__init__.py
algofunc/search.py
algofunc/sorts.py
algofunc-0.0.1.dist-info/METADATA
algofunc-0.0.1.dist-info/WHEEL
algofunc-0.0.1.dist-info/license_files/LICENSE
algofunc-0.0.1.dist-info/RECORD
