Metadata-Version: 2.1
Name: algofunc
Version: 0.0.1
Summary: A library of algorithm functions for Python
Project-URL: Documentation, https://github.com/alecnazworth/AlgoLib
Author-email: alecnazworth <alecnazworthalt@gmail.com>
License: MIT License
Classifier: License :: OSI Approved :: MIT License
Classifier: Operating System :: OS Independent
Classifier: Programming Language :: Python :: 3
Requires-Python: >=3.7
